fluxguard/__init__.py
fluxguard/analyzer.py
fluxguard/core.py
fluxguard/guards.py
fluxguard/reporter.py
fluxguard/storage.py
fluxguard/utils.py
fluxguard/adapters/asyncio_adapter.py
fluxguard/adapters/gevent_adapter.py
fluxguard/adapters/trio_adapter.py
fluxguard-0.1.0.dist-info/METADATA
fluxguard-0.1.0.dist-info/WHEEL
fluxguard-0.1.0.dist-info/top_level.txt
fluxguard-0.1.0.dist-info/RECORD
