Metadata-Version: 2.4
Name: fluxguard
Version: 0.1.0
Summary: Library for monitoring and adapting asynchronous Python code
Home-page: https://github.com/ksen145/fluxguard
Author: Egor Safonov
Author-email: ksen10405@gmail.com
Classifier: Programming Language :: Python :: 3
Classifier: License :: OSI Approved :: MIT License
Classifier: Operating System :: OS Independent
Requires-Python: >=3.7
Dynamic: author
Dynamic: author-email
Dynamic: classifier
Dynamic: description-content-type
Dynamic: home-page
Dynamic: requires-python
Dynamic: summary
